Multiple_Modules/Module_2.v
module Module_2(input_1_module_2, input_2_module_2, Z);

input input_1_module_2, input_2_module_2;
output Z;

assign Z = ~((input_1_module_2 | input_2_module_2) & (input_1_module_2 & input_2_module_2));


endmodule

Multiple_Modules/Module_1.v
module Module_1(A,B,C,D,output_1_module_1, output_2_module_1);

input A,B,C,D;
output output_1_module_1, output_2_module_1;

// interim signals

assign output_1_module_1 = ((A|B)&(C)) | (~(A&B));
assign output_2_module_1 = D;

endmodule

Multiple_Modules/Top_Level_Module.v
`include "Module_1.v"
`include "Module_2.v"

module Top_Level_Module(A,B,C,D,clk,reset,Z);

// declairing Inputs
input A,B,C,D,clk,reset;
// declairing Output
output Z;

// interim signals

reg [1:0] reg_output;
wire output_1_module_1, output_2_module_1;

// Module 1 Instantiation

Module_1 Module_1(
    .A(A),
    .B(B),
    .C(C),
    .D(D),
    .output_1_module_1(output_1_module_1), 
    .output_2_module_1(output_2_module_1)
);


always @ (posedge clk)
begin
  if(reset) begin
    reg_output <= 2'b00;
  end
  else begin
    reg_output[0] <= output_1_module_1;
    reg_output[1] <= output_2_module_1;
  end
end

Module_2 Module_2(
    .input_1_module_2(reg_output[0]), 
    .input_2_module_2(reg_output[1]), 
    .Z(Z)
);



endmodule

Multiple_Modules/testBench.v
module TB();

reg A,B,C,D,clk=0,reset;
wire Z;

Top_Level_Module dut(
    .A(A),
    .B(B),
    .C(C),
    .D(D),
    .clk(clk),
    .reset(reset),
    .Z(Z)
);

// creating clock

always begin
  clk = ~clk;
  #50;
end

 initial begin
    // Combination 0
    reset = 1'b1;
    D = 1'b0; C = 1'b0; B = 1'b0; A = 1'b0;
    
    #100;

    // Combination 1
    reset = 1'b0;
    D = 1'b0; C = 1'b0; B = 1'b0; A = 1'b1;
    #100;

    // Combination 2
    D = 1'b0; C = 1'b0; B = 1'b1; A = 1'b0;
    #100;

    // Combination 3
    D = 1'b0; C = 1'b0; B = 1'b1; A = 1'b1;
    #100;

    // Combination 4
    D = 1'b0; C = 1'b1; B = 1'b0; A = 1'b0;
    #100;

    // Combination 5
    D = 1'b0; C = 1'b1; B = 1'b0; A = 1'b1;
    #100;

    // Combination 6
    D = 1'b0; C = 1'b1; B = 1'b1; A = 1'b0;
    #100;

    // Combination 7
    D = 1'b0; C = 1'b1; B = 1'b1; A = 1'b1;
    #100;

    // Combination 8
    D = 1'b1; C = 1'b0; B = 1'b0; A = 1'b0;
    #100;

    // Combination 9
    D = 1'b1; C = 1'b0; B = 1'b0; A = 1'b1;
    #100;

    // Combination 10
    D = 1'b1; C = 1'b0; B = 1'b1; A = 1'b0;
    #100;

    // Combination 11
    D = 1'b1; C = 1'b0; B = 1'b1; A = 1'b1;
    #100;

    // Combination 12
    D = 1'b1; C = 1'b1; B = 1'b0; A = 1'b0;
    #100;

    // Combination 13
    D = 1'b1; C = 1'b1; B = 1'b0; A = 1'b1;
    #100;

    // Combination 14
    D = 1'b1; C = 1'b1; B = 1'b1; A = 1'b0;
    #100;

    // Combination 15
    D = 1'b1; C = 1'b1; B = 1'b1; A = 1'b1;
    #100;

    $finish; // End simulation
  end


initial begin
  $dumpfile("dump.vcd");
  $dumpvars(0);
end



endmodule

Multiple_Modules/dump.vcd
$date
	Thu Jan 11 22:48:30 2024
$end
$version
	Icarus Verilog
$end
$timescale
	1s
$end
$scope module TB $end
$var wire 1 ! Z $end
$var reg 1 " A $end
$var reg 1 # B $end
$var reg 1 $ C $end
$var reg 1 % D $end
$var reg 1 & clk $end
$var reg 1 ' reset $end
$scope module dut $end
$var wire 1 " A $end
$var wire 1 # B $end
$var wire 1 $ C $end
$var wire 1 % D $end
$var wire 1 & clk $end
$var wire 1 ' reset $end
$var wire 1 ( output_2_module_1 $end
$var wire 1 ) output_1_module_1 $end
$var wire 1 ! Z $end
$var reg 2 * reg_output [1:0] $end
$scope module Module_1 $end
$var wire 1 " A $end
$var wire 1 # B $end
$var wire 1 $ C $end
$var wire 1 % D $end
$var wire 1 ) output_1_module_1 $end
$var wire 1 ( output_2_module_1 $end
$upscope $end
$scope module Module_2 $end
$var wire 1 ! Z $end
$var wire 1 + input_1_module_2 $end
$var wire 1 , input_2_module_2 $end
$upscope $end
$upscope $end
$upscope $end
$enddefinitions $end
$comment Show the parameter values. $end
$dumpall
$end
#0
$dumpvars
0,
0+
b0 *
1)
0(
1'
1&
0%
0$
0#
0"
1!
$end
#50
0&
#100
1+
b1 *
1&
1"
0'
#150
0&
#200
1&
0"
1#
#250
0&
#300
0)
1&
1"
#350
0&
#400
0+
b0 *
1)
1&
0"
0#
1$
#450
0&
#500
1+
b1 *
1&
1"
#550
0&
#600
1&
0"
1#
#650
0&
#700
1&
1"
#750
0&
#800
0!
1,
b11 *
1)
1&
0"
0#
0$
1(
1%
#850
0&
#900
1&
1"
#950
0&
#1000
1&
0"
1#
#1050
0&
#1100
0)
1&
1"
#1150
0&
#1200
1!
0+
b10 *
1)
1&
0"
0#
1$
#1250
0&
#1300
0!
1+
b11 *
1&
1"
#1350
0&
#1400
1&
0"
1#
#1450
0&
#1500
1&
1"
