5_State_FSM/design.v
module FSM(clk, reset, req_0, req_1, req_2, req_3, gen_0, gen_1, gen_2, gen_3);

input clk, reset, req_0, req_1, req_2, req_3;
output reg gen_0, gen_1, gen_2, gen_3;

parameter IDLE = 3'b000, GEN0 = 3'b001, GEN1 = 3'b010, GEN2 = 3'b011, GEN3 = 3'b100;
reg [2:0] state, next_state;

// State Logic
always @ (posedge clk or posedge reset)
begin
  if(reset) begin
    state <= IDLE;
  end
  else begin
    state <= next_state;
  end
end
// Next State and Output
always @ (state or req_0 or req_1 or req_2 or req_3)
begin
  case (state)
  IDLE : if(req_0) begin
    gen_0 = 1;
    next_state = GEN0;
  end else if(req_1) begin
    gen_1 = 1;
    next_state = GEN1;
  end else if(req_2) begin
    gen_2 = 1;
    next_state = GEN2;
  end else if(req_3) begin
    gen_3 = 1;
    next_state = GEN3;
  end else begin
    gen_0 = 0;
    gen_1 = 0;
    gen_2 = 0;
    gen_3 = 0;
    next_state = IDLE;
  end
  GEN0 : if(req_0) begin
    gen_0 = 1;
  end else begin
    next_state = IDLE;
  end
  GEN1 : if(req_1) begin
    gen_1 = 1;
  end else begin
    next_state = IDLE;
  end
  GEN2 : if(req_2) begin
    gen_2 = 1;
  end else begin
    next_state = IDLE;
  end
  GEN3 : if(req_3) begin
    gen_3 = 1;
  end else begin
    next_state = IDLE;
  end
  endcase
end


endmodule

5_State_FSM/testBench.v
module FSM_TestBench();


reg clk=0, reset, req_0, req_1, req_2, req_3;
wire gen_0, gen_1, gen_2, gen_3;

FSM dut(
    .clk(clk), 
    .reset(reset), 
    .req_0(req_0), 
    .req_1(req_1), 
    .req_2(req_2), 
    .req_3(req_3), 
    .gen_0(gen_0), 
    .gen_1(gen_1), 
    .gen_2(gen_2), 
    .gen_3(gen_3)
    );

// Creating Clock

always begin
  clk <= ~clk;
  #50;
end

initial begin
  reset <= 1;
  #100;
  reset <= 0;
  #100;
  req_0 <= 1;
  #100;
  req_0 <= 0;
  #100;
  req_1 <= 1;
  #100;
  req_1 <= 0;
  #100;
  req_2 <= 1;
  #100;
  req_2 <= 0;
  #100;
  req_3 <= 1;
  #100;
  req_3 <= 0;
  #300;
  $finish;
end

initial begin
  $dumpfile("dump.vcd");
  $dumpvars(0);
end

endmodule

5_State_FSM/dump.vcd
$date
	Tue Jan 16 15:58:28 2024
$end
$version
	Icarus Verilog
$end
$timescale
	1s
$end
$scope module FSM_TestBench $end
$var wire 1 ! gen_3 $end
$var wire 1 " gen_2 $end
$var wire 1 # gen_1 $end
$var wire 1 $ gen_0 $end
$var reg 1 % clk $end
$var reg 1 & req_0 $end
$var reg 1 ' req_1 $end
$var reg 1 ( req_2 $end
$var reg 1 ) req_3 $end
$var reg 1 * reset $end
$scope module dut $end
$var wire 1 % clk $end
$var wire 1 & req_0 $end
$var wire 1 ' req_1 $end
$var wire 1 ( req_2 $end
$var wire 1 ) req_3 $end
$var wire 1 * reset $end
$var parameter 3 + GEN0 $end
$var parameter 3 , GEN1 $end
$var parameter 3 - GEN2 $end
$var parameter 32 . GEN3 $end
$var parameter 3 / IDLE $end
$var reg 1 $ gen_0 $end
$var reg 1 # gen_1 $end
$var reg 1 " gen_2 $end
$var reg 1 ! gen_3 $end
$var reg 3 0 next_state [2:0] $end
$var reg 3 1 state [2:0] $end
$upscope $end
$upscope $end
$enddefinitions $end
$comment Show the parameter values. $end
$dumpall
b0 /
b1101111 .
b11 -
b10 ,
b1 +
$end
#0
$dumpvars
b0 1
b0 0
1*
x)
x(
x'
x&
1%
0$
0#
0"
0!
$end
#50
0%
#100
1%
0*
#150
0%
#200
b1 1
b1 0
1$
1%
1&
#250
0%
#300
0$
b0 1
b0 0
1%
0&
#350
0%
#400
b10 1
b10 0
1#
1%
1'
#450
0%
#500
0#
b0 1
b0 0
1%
0'
#550
0%
#600
b11 1
b11 0
1"
1%
1(
#650
0%
#700
0"
b0 1
b0 0
1%
0(
#750
0%
#800
b111 1
b111 0
1!
1%
1)
#850
0%
#900
1%
0)
