Up_Counter/design.v
module Up_Counter(clk, reset, data_out);

input clk, reset;
output reg [3:0] data_out;

always @ (posedge clk or posedge reset)
begin
  if(reset) begin
    data_out <= 4'b000;
  end
  else begin
    data_out <= data_out + 1'b1;
  end
end

endmodule

Up_Counter/testBench.v
module TB();

reg clk=0, reset;
wire [3:0] data_out;

Up_Counter dut(
  .clk(clk),
  .reset(reset),
  .data_out(data_out)
);

// Creating Clock

always begin
  clk <= ~clk;
  #50;
end

initial begin
  reset <=1;
  #100;
  reset <=0;
  #600; // You Can set according to you
  $finish;
end

initial begin
  $dumpfile("dump.vcd");
  $dumpvars(0);
end

endmodule

Up_Counter/dump.vcd
$date
	Mon Jan 15 22:31:00 2024
$end
$version
	Icarus Verilog
$end
$timescale
	1s
$end
$scope module TB $end
$var wire 4 ! data_out [3:0] $end
$var reg 1 " clk $end
$var reg 1 # reset $end
$scope module dut $end
$var wire 1 " clk $end
$var wire 1 # reset $end
$var reg 4 $ data_out [3:0] $end
$upscope $end
$upscope $end
$enddefinitions $end
$comment Show the parameter values. $end
$dumpall
$end
#0
$dumpvars
b0 $
1#
1"
b0 !
$end
#50
0"
#100
b1 !
b1 $
1"
0#
#150
0"
#200
b10 !
b10 $
1"
#250
0"
#300
b11 !
b11 $
1"
#350
0"
#400
b100 !
b100 $
1"
#450
0"
#500
b101 !
b101 $
1"
#550
0"
#600
b110 !
b110 $
1"
#650
0"
#700
b111 !
b111 $
1"
