Encoder/design.v

// Encoder 16x4

module Encoder(Encoder_In, Binary_Out);

input [15:0] Encoder_In;
output reg [3:0] Binary_Out;

always @ (Encoder_In)
begin
  case (Encoder_In)
  16'h0: begin
    Binary_Out <= 4'b0000;
  end
  16'h1: begin
    Binary_Out <= 4'b0001;
  end
  16'h2: begin
    Binary_Out <= 4'b0010;
  end
  16'h3: begin
    Binary_Out <= 4'b0011;
  end
  16'h4: begin
    Binary_Out <= 4'b0100;
  end
  16'h5: begin
    Binary_Out <= 4'b0101;
  end
  16'h6: begin
    Binary_Out <= 4'b0110;
  end
  16'h7: begin
    Binary_Out <= 4'b0111;
  end
  16'h8: begin
    Binary_Out <= 4'b1000;
  end
  16'h9: begin
    Binary_Out <= 4'b1001;
  end
  16'hA: begin
    Binary_Out <= 4'b1010;
  end
  16'hB: begin
    Binary_Out <= 4'b1011;
  end
  16'hC: begin
    Binary_Out <= 4'b1100;
  end
  16'hD: begin
    Binary_Out <= 4'b1101;
  end
  16'hE: begin
    Binary_Out <= 4'b1110;
  end
  16'hF: begin
    Binary_Out <= 4'b1111;
  end
  default: begin
    Binary_Out <= 4'b0000;
  end
  endcase
end

endmodule

Encoder/testBench.v

module TB();
reg [15:0] Encoder_In;
wire [3:0] Binary_Out;

Encoder dut(
  .Encoder_In(Encoder_In), 
  .Binary_Out(Binary_Out)
  );

initial begin
  Encoder_In <= 16'h0;
  #100;
  Encoder_In <= 16'h1;
  #100;
  Encoder_In <= 16'h2;
  #100;
  Encoder_In <= 16'h3;
  #100;
  Encoder_In <= 16'h4;
  #100;
  Encoder_In <= 16'h5;
  #100;
  Encoder_In <= 16'h6;
  #100;
  Encoder_In <= 16'h7;
  #100;
  Encoder_In <= 16'h8;
  #100;
  Encoder_In <= 16'h9;
  #100;
  Encoder_In <= 16'hA;
  #100;
  
end


initial begin
  $dumpfile("dump.vcd");
  $dumpvars(0);
end

endmodule

Encoder/dump.vcd
$date
	Mon Jan 15 19:15:04 2024
$end
$version
	Icarus Verilog
$end
$timescale
	1s
$end
$scope module TB $end
$var wire 4 ! Binary_Out [3:0] $end
$var reg 16 " Encoder_In [15:0] $end
$scope module dut $end
$var wire 16 # Encoder_In [15:0] $end
$var reg 4 $ Binary_Out [3:0] $end
$upscope $end
$upscope $end
$enddefinitions $end
$comment Show the parameter values. $end
$dumpall
$end
#0
$dumpvars
b0 $
b0 #
b0 "
b0 !
$end
#100
b1 !
b1 $
b1 "
b1 #
#200
b10 !
b10 $
b10 "
b10 #
#300
b11 !
b11 $
b11 "
b11 #
#400
b100 !
b100 $
b100 "
b100 #
#500
b101 !
b101 $
b101 "
b101 #
#600
b110 !
b110 $
b110 "
b110 #
#700
b111 !
b111 $
b111 "
b111 #
#800
b1000 !
b1000 $
b1000 "
b1000 #
#900
b1001 !
b1001 $
b1001 "
b1001 #
#1000
b1010 !
b1010 $
b1010 "
b1010 #
