If_Else/design.v

module Mux(a,b,s,out);

input a,b,s;
output reg out;

always @ (a or b or s)
begin
  if(s == 1'b1) begin
    out = a;
  end
  else begin
    out = b;
  end
end

endmodule

If_Else/testBench.v

module TB();

reg a,b,s;
wire out;

Mux dut(
    .a(a),
    .b(b),
    .s(s),
    .out(out)

);

initial begin
  a=1'b0; b=1'b0; s=1'b0;
  #100;
  a=1'b0; b=1'b0; s=1'b1;
  #100;
  a=1'b0; b=1'b1; s=1'b0;
  #100;
  a=1'b0; b=1'b1; s=1'b1;
  #100;
  a=1'b1; b=1'b0; s=1'b0;
  #100;
  a=1'b1; b=1'b0; s=1'b1;
  #100;
  a=1'b1; b=1'b1; s=1'b0;
  #100;
  a=1'b1; b=1'b1; s=1'b1;
  #100;
  
end

initial begin
  $dumpfile("dump.vcd");
  $dumpvars(0);
end

endmodule;

If_Else/dump.vcd
$date
	Thu Jan 11 15:18:20 2024
$end
$version
	Icarus Verilog
$end
$timescale
	1s
$end
$scope module TB $end
$var wire 1 ! out $end
$var reg 1 " a $end
$var reg 1 # b $end
$var reg 1 $ s $end
$scope module dut $end
$var wire 1 " a $end
$var wire 1 # b $end
$var wire 1 $ s $end
$var reg 1 ! out $end
$upscope $end
$upscope $end
$enddefinitions $end
$comment Show the parameter values. $end
$dumpall
$end
#0
$dumpvars
0$
0#
0"
0!
$end
#100
1$
#200
1!
0$
1#
#300
0!
1$
#400
0$
0#
1"
#500
1!
1$
#600
0$
1#
#700
1$
