Seq_Circuit/design.v

module Sequential_Circuit(a,b,c,clk,reset,z);

input a,b,c,clk,reset;
output z;

// Nets
wire reg_1_Input;
wire reg_2_Input;
reg reg_1;
reg reg_2;

assign reg_1_Input = (a|b)&c;
assign reg_2_Input = ~(reg_1);
always @ (posedge clk)
begin
  if(reset) begin
    reg_1 <= 1'b0;
    reg_2 <= 1'b0;
  end
  else begin
    reg_1 <= reg_1_Input;
    reg_2 <= reg_2_Input;
  end
end

assign z = ~(reg_2);



endmodule

Seq_Circuit/testBench.v

module TB();

reg a, b, c, reset, clk=0;
wire z;

Sequential_Circuit dut(
    .a(a),
    .b(b),
    .c(c),
    .clk(clk),
    .reset(reset),
    .z(z)
);

// create a clock

always begin
  clk = ~clk;
  #50;
end

initial begin
  reset = 1'b1;
  #100;
  reset = 1'b0;
  a = 1'b0;
  b = 1'b0;
  c = 1'b0;
  #100;
  reset = 1'b0;
  a = 1'b0;
  b = 1'b0;
  c = 1'b1;
  #100;
  reset = 1'b0;
  a = 1'b0;
  b = 1'b1;
  c = 1'b0;
  #100;
  reset = 1'b0;
  a = 1'b0;
  b = 1'b1;
  c = 1'b1;
  #100;
  reset = 1'b0;
  a = 1'b1;
  b = 1'b0;
  c = 1'b0;
  #100;
  reset = 1'b0;
  a = 1'b1;
  b = 1'b0;
  c = 1'b1;
  #100;
  reset = 1'b0;
  a = 1'b1;
  b = 1'b1;
  c = 1'b0;
  #100;
  reset = 1'b0;
  a = 1'b1;
  b = 1'b1;
  c = 1'b1;
  #100;
  $finish;
end

initial begin
  $dumpfile("seq.vcd");
  $dumpvars(0);
end


endmodule;

Seq_Circuit/seq.vcd
$date
	Thu Jan 11 00:45:28 2024
$end
$version
	Icarus Verilog
$end
$timescale
	1s
$end
$scope module TB $end
$var wire 1 ! z $end
$var reg 1 " a $end
$var reg 1 # b $end
$var reg 1 $ c $end
$var reg 1 % clk $end
$var reg 1 & reset $end
$scope module dut $end
$var wire 1 " a $end
$var wire 1 # b $end
$var wire 1 $ c $end
$var wire 1 % clk $end
$var wire 1 ' reg_1_Input $end
$var wire 1 ( reg_2_Input $end
$var wire 1 & reset $end
$var wire 1 ! z $end
$var reg 1 ) reg_1 $end
$var reg 1 * reg_2 $end
$upscope $end
$upscope $end
$enddefinitions $end
$comment Show the parameter values. $end
$dumpall
$end
#0
$dumpvars
0*
0)
1(
x'
1&
1%
x$
x#
x"
1!
$end
#50
0%
#100
0!
1*
0'
1%
0$
0#
0"
0&
#150
0%
#200
1%
1$
#250
0%
#300
1%
0$
1#
#350
0%
#400
0(
1)
1'
1%
1$
#450
0%
#500
1!
1(
0*
0)
0'
1%
0$
0#
1"
#550
0%
#600
0!
0(
1*
1)
1'
1%
1$
#650
0%
#700
1!
1(
0*
0)
0'
1%
0$
1#
#750
0%
#800
0!
0(
1*
1)
1'
1%
1$
#850
0%
#900
1!
0*
1%
