Combinational_Circuit/combCircuit.v
module combinationalLogic(A,B,C,Q);

input A,B,C;
output Q;
wire E,F;

assign E = ~(A&B);
assign F = ~(A|B);
assign Q = E&F&C;

endmodule;

Combinational_Circuit/TB_combCircuit.v

module TB();

reg A,B,C;
wire Q;

combinationalLogic dut(
    .A(A),
    .B(B),
    .C(C),
    .Q(Q)
);

initial begin
    A<=1'b0; B<=1'b0; C<=1'b0;
    #100;
    A<=1'b0; B<=1'b0; C<=1'b1;
    #100;
    A<=1'b0; B<=1'b1; C<=1'b0;
    #100;
    A<=1'b0; B<=1'b1; C<=1'b1;
    #100;
    A<=1'b1; B<=1'b0; C<=1'b0;
    #100;
    A<=1'b1; B<=1'b0; C<=1'b1;
    #100;
    A<=1'b1; B<=1'b1; C<=1'b0;
    #100;
    A<=1'b1; B<=1'b1; C<=1'b1;
    #100;
end

initial begin
    $dumpfile("dump.vcd");
    $dumpvars(0);
end

endmodule;

Combinational_Circuit/dump.vcd
$date
	Tue Jan 09 01:56:23 2024
$end
$version
	Icarus Verilog
$end
$timescale
	1s
$end
$scope module TB $end
$var wire 1 ! Q $end
$var reg 1 " A $end
$var reg 1 # B $end
$var reg 1 $ C $end
$scope module dut $end
$var wire 1 " A $end
$var wire 1 # B $end
$var wire 1 $ C $end
$var wire 1 % E $end
$var wire 1 & F $end
$var wire 1 ! Q $end
$upscope $end
$upscope $end
$enddefinitions $end
$comment Show the parameter values. $end
$dumpall
$end
#0
$dumpvars
1&
1%
0$
0#
0"
0!
$end
#100
1!
1$
#200
0&
0!
0$
1#
#300
1$
#400
0$
0#
1"
#500
1$
#600
0%
0$
1#
#700
1$
